{"title":"3.磁铁的相互作用力之小结+后续导入","date":"2018-01-05T09:15:26.000Z","slug":"unit3","tags":["小学三年级科学下册","浙江教育出版社","第三课时","第四单元磁铁"],"updated":"2019-01-05T16:21:15.892Z","content":"<h3 id=\"课时3\"><a href=\"#课时3\" class=\"headerlink\" title=\"课时3\"></a><u>课时3</u></h3><h5 id=\"上节测验答案是：南、北，你答对了吗？\"><a href=\"#上节测验答案是：南、北，你答对了吗？\" class=\"headerlink\" title=\"上节测验答案是：南、北，你答对了吗？\"></a><u>上节测验答案是：南、北，你答对了吗？</u></h5><h4 id=\"“悬挂法”得出的结论\"><a href=\"#“悬挂法”得出的结论\" class=\"headerlink\" title=\"“悬挂法”得出的结论\"></a><u>“悬挂法”得出的结论</u></h4><p><strong>1.我们将磁铁指向北极的一极称为北极</strong></p>\n<p><strong>2.我们将磁铁指向南极的一极称为南极</strong></p>\n<p><strong>3.我们用“N”表示北极，用“S”表示南极</strong></p>\n<div class=\"article-img\"><p><img src=\"https://ws1.sinaimg.cn/large/005FZoJFly1fyvtvu68tfj30er0b4q3v.jpg\" alt=\"\"></p></div>\n<h4 id=\"回答问题2：\"><a href=\"#回答问题2：\" class=\"headerlink\" title=\"回答问题2：\"></a><u>回答问题2：</u></h4><p><strong>有时候两块磁铁会相互吸引，有时候两块磁铁会相互排斥，这是为什么？</strong><br><img src=\"https://ws1.sinaimg.cn/large/005FZoJFly1fyvtwlepggj305y07ywex.jpg\" alt=\"\"></p>\n<p><strong><u>因为磁铁之间有相互作用力。</u></strong></p>\n<p><strong>那么我们如何来确定是吸引的作用力还是排斥的作用力呢？</strong><br><strong>仔细开动脑经写下你们的想法，我们第四课时揭晓答案。</strong></p>\n<div class=\"article-img\"><p><img src=\"https://ws1.sinaimg.cn/large/005FZoJFly1fyvswfsl0pj303k03kt98.jpg\" alt=\"\"></p></div>\n<!--高速版-->\n<p><div id=\"SOHUCS\"></div></p>\n<script charset=\"utf-8\" type=\"text/javascript\" src=\"http://changyan.sohu.com/upload/changyan.js\"></script>\n<div class=\"is-snippet\"><script>(function(){window.changyan.api.config({\nappid: 'cyu1hmwgd',\nconf: 'prod_6704ab3a4a7b6af8e8ae05fa63404e3a'\n});})();</script></div>\n\n\n","prev":{"title":"4.磁铁的相互作用力之作用力实验","slug":"unit4"},"next":{"title":"2.磁铁的相互作用力之答案展示+测验","slug":"unit2"},"link":"http://yoursite.com/post/unit3/","reward":true}